README.rst
setup.py
notesplit/__init__.py
notesplit/split.py
notesplit/sync.py
notesplit/syncfiles.py
notesplit.egg-info/PKG-INFO
notesplit.egg-info/SOURCES.txt
notesplit.egg-info/dependency_links.txt
notesplit.egg-info/entry_points.txt
notesplit.egg-info/not-zip-safe
notesplit.egg-info/requires.txt
notesplit.egg-info/top_level.txt