Metadata-Version: 2.1
Name: notesplit
Version: 1.1.0
Summary: Write your private diary in text files, and share parts of it with someone else's diaries.
Home-page: https://github.com/mindey/notesplit
Author: Mindey
Author-email: ~@mindey.com
License: MIT
Platform: UNKNOWN
Provides-Extra: test
